buildantic/__init__.py
buildantic/descriptor/__init__.py
buildantic/descriptor/base.py
buildantic/descriptor/openapi/__init__.py
buildantic/descriptor/openapi/types.py
buildantic/descriptor/openapi/utils.py
buildantic/descriptor/python.py
buildantic/registry/__init__.py
buildantic/registry/base.py
buildantic/registry/openapi.py
buildantic/registry/python.py
buildantic/utils.py
buildantic/validator.py
buildantic-0.0.1.dist-info/LICENSE
buildantic-0.0.1.dist-info/METADATA
buildantic-0.0.1.dist-info/WHEEL
buildantic-0.0.1.dist-info/RECORD
