Metadata-Version: 2.1
Name: buildantic
Version: 0.0.1
Summary: JSON schema generation and data validation, with native support for LLM function-calling formats
Home-page: https://github.com/synacktraa/buildantic
Author: Harsh Verma
Author-email: synacktra.work@gmail.com
Requires-Python: >=3.8,<3.13
Classifier: Programming Language :: Python :: 3
Classifier: Programming Language :: Python :: 3.8
Classifier: Programming Language :: Python :: 3.9
Classifier: Programming Language :: Python :: 3.10
Classifier: Programming Language :: Python :: 3.11
Classifier: Programming Language :: Python :: 3.12
Requires-Dist: docstring-parser (>=0.15)
Requires-Dist: jsonref (>=1.1.0)
Requires-Dist: jsonschema (>=4.21.0)
Requires-Dist: pydantic (>=2.0.0)
Project-URL: Documentation, https://synacktraa.github.io/buildantic/
Project-URL: Repository, https://github.com/synacktraa/buildantic
